csvskim/__init__.py
csvskim/__main__.py
csvskim/cli.py
csvskim/lib.py
csvskim-0.1.dist-info/METADATA
csvskim-0.1.dist-info/WHEEL
csvskim-0.1.dist-info/entry_points.txt
csvskim-0.1.dist-info/top_level.txt
csvskim-0.1.dist-info/RECORD
